sqrm/__init__.py
sqrm/core.py
sqrm-0.1.0.dist-info/METADATA
sqrm-0.1.0.dist-info/WHEEL
sqrm-0.1.0.dist-info/entry_points.txt
sqrm-0.1.0.dist-info/top_level.txt
sqrm-0.1.0.dist-info/RECORD
