Metadata-Version: 2.1
Name: sqrm
Version: 0.1.0
Summary: Simple QR-based Warehouse Management System
Author: Your Name
Author-email: your.email@example.com
Classifier: Development Status :: 3 - Alpha
Classifier: Intended Audience :: Developers
Classifier: License :: OSI Approved :: MIT License
Classifier: Operating System :: OS Independent
Classifier: Programming Language :: Python :: 3
Classifier: Programming Language :: Python :: 3.6
Classifier: Programming Language :: Python :: 3.7
Classifier: Programming Language :: Python :: 3.8
Classifier: Programming Language :: Python :: 3.9
Requires-Python: >=3.6
Requires-Dist: qrcode>=7.3
Requires-Dist: opencv-python>=4.5
Requires-Dist: pandas>=1.3
Requires-Dist: numpy>=1.21
